{
  "format_version": "1.26.30",
  "minecraft:item": {
    "description": {
      "identifier": "toolsplusplus:ruby_shovel",
      "menu_category": {
        "category": "equipment",
        "group": "minecraft:itemGroup.name.shovel"
      }
    },
    "components": {
      "minecraft:icon": "toolsplusplus:ruby_shovel",
      "minecraft:max_stack_size": 1,
      "minecraft:hand_equipped": true,
      "minecraft:durability": {
        "max_durability": 875
      },
      "toolsplusplus:digging_durability": {},
      "minecraft:digger": {
        "use_efficiency": true,
        "destroy_speeds": [
          {
            "block": {
              "tags": "q.any_tag('minecraft:is_shovel_item_destructible')"
            },
            "speed": 7
          }
        ]
      },
      "minecraft:enchantable": {
        "slot": "shovel",
        "value": 10
      },
      "minecraft:repairable": {
        "repair_items": [
          {
            "items": ["toolsplusplus:ruby_shovel"],
            "repair_amount": "context.other->query.remaining_durability"
          },
          {
            "items": ["toolsplusplus:ruby"],
            "repair_amount": "query.max_durability * 0.25"
          }
        ]
      },
      "minecraft:tags": {
        "tags": [
          "minecraft:is_tool",
          "minecraft:is_shovel",
          "toolsplusplus:ruby_tier",
          "minecraft:iron_tier_destructible"
        ]
      }
    }
  }
}
